arrayqueues/__init__.py
arrayqueues/portable_queue.py
arrayqueues/shared_arrays.py
arrayqueues-1.4.1.dist-info/LICENSE.txt
arrayqueues-1.4.1.dist-info/METADATA
arrayqueues-1.4.1.dist-info/WHEEL
arrayqueues-1.4.1.dist-info/top_level.txt
arrayqueues-1.4.1.dist-info/RECORD
